oryks_google_drive/__init__.py
oryks_google_drive/config.py
oryks_google_drive/gdrive.py
oryks_google_drive/mime_types.py
oryks_google_drive/exceptions/__init__.py
oryks_google_drive/exceptions/authentication.py
oryks_google_drive/exceptions/authorization.py
oryks_google_drive/models/__init__.py
oryks_google_drive/resources/__init__.py
oryks_google_drive/schemas/__init__.py
oryks_google_drive-0.1.5.dist-info/licenses/LICENSE
oryks_google_drive-0.1.5.dist-info/METADATA
oryks_google_drive-0.1.5.dist-info/WHEEL
oryks_google_drive-0.1.5.dist-info/top_level.txt
oryks_google_drive-0.1.5.dist-info/RECORD
