Metadata-Version: 2.4
Name: oryks_google_drive
Version: 0.1.5
Summary: A python library for working with Google Drive.
Home-page: https://youtube-wrapper.readthedocs.io/en/latest/index.html
Author: Lyle Okoth
Author-email: lyceokoth@gmail.com
License: MIT
Keywords: drive,google-drive,google-drive-api,upload files to Google Drive
Classifier: Intended Audience :: Developers
Classifier: License :: OSI Approved :: MIT License
Classifier: Programming Language :: Python
Classifier: Programming Language :: Python :: 3
Classifier: Programming Language :: Python :: 3.11
Classifier: Programming Language :: Python :: 3.12
Classifier: Operating System :: OS Independent
License-File: LICENSE
Requires-Dist: gverify
Requires-Dist: pydantic
Requires-Dist: pydantic-settings
Dynamic: author
Dynamic: author-email
Dynamic: classifier
Dynamic: description
Dynamic: description-content-type
Dynamic: home-page
Dynamic: keywords
Dynamic: license
Dynamic: license-file
Dynamic: requires-dist
Dynamic: summary
